easyAdobeAnalytics/__init__.py
easyAdobeAnalytics/clean_adobe_response.py
easyadobeanalytics-1.0.3.dist-info/LICENSE
easyadobeanalytics-1.0.3.dist-info/METADATA
easyadobeanalytics-1.0.3.dist-info/WHEEL
easyadobeanalytics-1.0.3.dist-info/top_level.txt
easyadobeanalytics-1.0.3.dist-info/RECORD
