Metadata-Version: 2.1
Name: easyadobeanalytics
Version: 1.0.3
Summary: This is an attempt at a usable python library to query report data from Adobe Analytics 1.4 API.
Home-page: https://github.com/varnitsingh/easyAdobeAnalytics
Author: Varnit Singh
Author-email: 
Project-URL: Homepage, https://github.com/varnitsingh/easyAdobeAnalytics
Project-URL: Issues, https://github.com/varnitsingh/easyAdobeAnalytics/issues
Classifier: Programming Language :: Python :: 3
Classifier: License :: OSI Approved :: Apache Software License
Classifier: Operating System :: OS Independent
Requires-Python: >=3.10
License-File: LICENSE
Requires-Dist: pandas>=2.2.3
Requires-Dist: requests>=2.32.3
